quantlaw/__init__.py
quantlaw/de_extract/__init__.py
quantlaw/de_extract/load_statute_names.py
quantlaw/de_extract/statutes_abstract.py
quantlaw/de_extract/statutes_areas.py
quantlaw/de_extract/statutes_areas_patterns.py
quantlaw/de_extract/statutes_parse.py
quantlaw/de_extract/statutes_parse_patterns.py
quantlaw/de_extract/stemming.py
quantlaw/utils/__init__.py
quantlaw/utils/beautiful_soup.py
quantlaw/utils/files.py
quantlaw/utils/networkx.py
quantlaw/utils/pipeline.py
quantlaw-0.0.7.dist-info/AUTHORS.rst
quantlaw-0.0.7.dist-info/LICENSE.txt
quantlaw-0.0.7.dist-info/METADATA
quantlaw-0.0.7.dist-info/WHEEL
quantlaw-0.0.7.dist-info/top_level.txt
quantlaw-0.0.7.dist-info/RECORD
