Metadata-Version: 2.1
Name: quantlaw
Version: 0.0.7
Summary: Coding utilities for quantitative legal studies
Home-page: https://github.com/quantlaw/quantlaw/
Author: QuantLaw Research Group
Author-email: mail@quantlaw.io
License: new-bsd
Project-URL: Documentation, https://quantlaw.readthedocs.io/
Platform: any
Classifier: Development Status :: 4 - Beta
Classifier: Programming Language :: Python
Requires-Dist: regex
Requires-Dist: beautifulsoup4
Requires-Dist: lxml
Requires-Dist: networkx >=2.4
Requires-Dist: requests
Requires-Dist: pandas
Provides-Extra: testing
Requires-Dist: pytest ; extra == 'testing'
Requires-Dist: pytest-cov ; extra == 'testing'
